spacex_py/__init__.py
spacex_py/capsules.py
spacex_py/cores.py
spacex_py/info.py
spacex_py/launches.py
spacex_py/launchpads.py
spacex_py/rockets.py
spacex_py/_helpers/__init__.py
spacex_py/_helpers/_api.py
spacex_py-1.0.0.dist-info/METADATA
spacex_py-1.0.0.dist-info/RECORD
spacex_py-1.0.0.dist-info/WHEEL
spacex_py-1.0.0.dist-info/top_level.txt
