Metadata-Version: 2.1
Name: spacex-py
Version: 1.0.0
Summary: Python wrapper for the SpaceX API
Home-page: https://github.com/HiKaylum/SpaceX-PY
Author: Kaylum Lally
Author-email: kaylum@hikaylum.me
License: UNKNOWN
Platform: UNKNOWN
Classifier: Programming Language :: Python :: 3
Classifier: License :: OSI Approved :: MIT License
Classifier: Operating System :: OS Independent
Requires-Dist: requests
